proper_gator/__init__.py
proper_gator/authentication.py
proper_gator/cli.py
proper_gator/containers.py
proper_gator/proper_gator.py
proper_gator/service.py
proper_gator/tags.py
proper_gator/triggers.py
proper_gator/variables.py
proper_gator/workspaces.py
proper_gator-0.1.0.dist-info/entry_points.txt
proper_gator-0.1.0.dist-info/LICENSE
proper_gator-0.1.0.dist-info/WHEEL
proper_gator-0.1.0.dist-info/METADATA
proper_gator-0.1.0.dist-info/RECORD
